{
    "DataType": "ProceduralGridItemData",
    "DataVersion": 0,
    "GameVersion": "0.3.3f15",
    "GUID": "ad57faa5-8f0f-47a2-a1db-9ea55444e69c",
    "ItemString": "{\n    \"DataType\": \"ItemData\",\n    \"DataVersion\": 0,\n    \"GameVersion\": \"0.3.3f15\",\n    \"ID\": \"fullspectrumgrowlight\",\n    \"Quantity\": 1\n}",
    "LoadOrder": 50,
    "Rotation": 0,
    "FootprintMatches": [
        {
            "TileOwnerGUID": "1c159da8-a65d-44c6-9414-0fe6b96eeb97",
            "TileIndex": 2,
            "FootprintCoordinate": {
                "x": 0.0,
                "y": 0.0
            }
        },
        {
            "TileOwnerGUID": "1c159da8-a65d-44c6-9414-0fe6b96eeb97",
            "TileIndex": 1,
            "FootprintCoordinate": {
                "x": 0.0,
                "y": 1.0
            }
        },
        {
            "TileOwnerGUID": "1c159da8-a65d-44c6-9414-0fe6b96eeb97",
            "TileIndex": 3,
            "FootprintCoordinate": {
                "x": 1.0,
                "y": 0.0
            }
        },
        {
            "TileOwnerGUID": "1c159da8-a65d-44c6-9414-0fe6b96eeb97",
            "TileIndex": 0,
            "FootprintCoordinate": {
                "x": 1.0,
                "y": 1.0
            }
        }
    ]
}