{
    "DataType": "PackagerData",
    "DataVersion": 0,
    "GameVersion": "0.3.4f4",
    "ID": "kevin_scott",
    "AssignedProperty": "dockswarehouse",
    "FirstName": "Kevin",
    "LastName": "Scott",
    "IsMale": true,
    "AppearanceIndex": 5,
    "Position": {
        "x": -90.71894836425781,
        "y": -2.2300009727478029,
        "z": -40.554927825927737
    },
    "Rotation": {
        "x": 0.0,
        "y": -0.25881990790367129,
        "z": 0.0,
        "w": 0.9659256339073181
    },
    "GUID": "1bce0f7b-9077-46e8-a9f5-2b9395a99433",
    "PaidForToday": true,
    "MoveItemData": {
        "TemplateItemJSON": "",
        "GrabbedItemQuantity": 0,
        "SourceGUID": "",
        "DestinationGUID": ""
    }
}