{
    "DataType": "PlaceableStorageData",
    "DataVersion": 0,
    "GameVersion": "0.3.4f4",
    "GUID": "58dd52f5-d6fe-4e35-b64f-f1ebf08c415c",
    "ItemString": "{\n    \"DataType\": \"ItemData\",\n    \"DataVersion\": 0,\n    \"GameVersion\": \"0.3.4f4\",\n    \"ID\": \"largestoragerack\",\n    \"Quantity\": 1\n}",
    "LoadOrder": 0,
    "GridGUID": "efc3aaed-d40e-4075-8fc5-79664c851628",
    "OriginCoordinate": {
        "x": 9.0,
        "y": 7.0
    },
    "Rotation": 90,
    "Contents": {
        "Items": [
            "{\"DataType\":\"WeedData\",\"DataVersion\":0,\"GameVersion\":\"0.3.4f4\",\"ID\":\"granddaddypurple\",\"Quantity\":10,\"Quality\":\"Standard\",\"PackagingID\":\"\"}",
            "{\"DataType\":\"ItemData\",\"DataVersion\":0,\"GameVersion\":\"0.3.4f4\",\"ID\":\"cuke\",\"Quantity\":8}",
            "{\"DataType\":\"ItemData\",\"DataVersion\":0,\"GameVersion\":\"0.3.4f4\",\"ID\":\"TV\",\"Quantity\":1}",
            "{\"DataType\":\"ItemData\",\"DataVersion\":0,\"GameVersion\":\"0.3.4f4\",\"ID\":\"mouthwash\",\"Quantity\":1}",
            "{\"DataType\":\"ItemData\",\"DataVersion\":0,\"GameVersion\":\"0.3.4f4\",\"ID\":\"viagra\",\"Quantity\":1}",
            "{\"DataType\":\"ItemData\",\"DataVersion\":0,\"GameVersion\":\"0.3.4f4\",\"ID\":\"donut\",\"Quantity\":2}",
            "{\"DataType\":\"ItemData\",\"DataVersion\":0,\"GameVersion\":\"0.3.4f4\",\"ID\":\"pgr\",\"Quantity\":4}",
            "{\"DataType\":\"ItemData\",\"DataVersion\":0,\"GameVersion\":\"0.3.4f4\",\"ID\":\"fertilizer\",\"Quantity\":3}"
        ]
    }
}