{
    "DataType": "BotanistData",
    "DataVersion": 0,
    "GameVersion": "0.3.4f4",
    "ID": "ryan_obama",
    "AssignedProperty": "bungalow",
    "FirstName": "Ryan",
    "LastName": "Obama",
    "IsMale": true,
    "AppearanceIndex": 6,
    "Position": {
        "x": -168.78903198242188,
        "y": -4.036708831787109,
        "z": 109.44397735595703
    },
    "Rotation": {
        "x": 0.0,
        "y": 0.6997066140174866,
        "z": 0.0,
        "w": 0.7144303321838379
    },
    "GUID": "fc4784b1-06db-4752-b04e-48cc222e71e8",
    "PaidForToday": false,
    "MoveItemData": {
        "TemplateItemJSON": "",
        "GrabbedItemQuantity": 0,
        "SourceGUID": "",
        "DestinationGUID": ""
    }
}