{
    "DataType": "ProceduralGridItemData",
    "DataVersion": 0,
    "GameVersion": "0.3.3f15",
    "GUID": "a0899453-e42f-4b44-8a45-9f67cd77ca1d",
    "ItemString": "{\n    \"DataType\": \"ItemData\",\n    \"DataVersion\": 0,\n    \"GameVersion\": \"0.3.3f15\",\n    \"ID\": \"ledgrowlight\",\n    \"Quantity\": 1\n}",
    "LoadOrder": 50,
    "Rotation": 0,
    "FootprintMatches": [
        {
            "TileOwnerGUID": "61e8599b-2106-4cc2-9bfc-ab379b4d4c86",
            "TileIndex": 2,
            "FootprintCoordinate": {
                "x": 0.0,
                "y": 0.0
            }
        },
        {
            "TileOwnerGUID": "61e8599b-2106-4cc2-9bfc-ab379b4d4c86",
            "TileIndex": 1,
            "FootprintCoordinate": {
                "x": 0.0,
                "y": 1.0
            }
        },
        {
            "TileOwnerGUID": "61e8599b-2106-4cc2-9bfc-ab379b4d4c86",
            "TileIndex": 3,
            "FootprintCoordinate": {
                "x": 1.0,
                "y": 0.0
            }
        },
        {
            "TileOwnerGUID": "61e8599b-2106-4cc2-9bfc-ab379b4d4c86",
            "TileIndex": 0,
            "FootprintCoordinate": {
                "x": 1.0,
                "y": 1.0
            }
        }
    ]
}