{
    "DataType": "CustomerData",
    "DataVersion": 0,
    "GameVersion": "0.3.4f4",
    "Dependence": 0.9274999499320984,
    "PurchaseableProducts": [
        "strawberrybud"
    ],
    "ProductAffinities": [
        0.853759229183197,
        -0.38329994678497317,
        1.0
    ],
    "TimeSinceLastDealCompleted": 1679,
    "TimeSinceLastDealOffered": 375,
    "OfferedDeals": 28,
    "CompletedDeals": 27,
    "IsContractOffered": false,
    "OfferedContract": {
        "Payment": 0.0,
        "Products": {
            "entries": []
        },
        "DeliveryLocationGUID": "",
        "DeliveryWindow": {
            "IsEnabled": false,
            "WindowStartTime": 1200,
            "WindowEndTime": 1800
        },
        "Expires": false,
        "ExpiresAfter": 0,
        "PickupScheduleIndex": 0,
        "IsCounterOffer": false
    },
    "OfferedContractTime": {
        "elapsedDays": 55,
        "time": 1645
    },
    "TimeSincePlayerApproached": 1104303,
    "TimeSinceInstantDealOffered": 1104303,
    "HasBeenRecommended": false
}