{
    "DataType": "CustomerData",
    "DataVersion": 0,
    "GameVersion": "0.3.4f4",
    "Dependence": 0.5874999761581421,
    "PurchaseableProducts": [
        "strawberrybud"
    ],
    "ProductAffinities": [
        1.0,
        0.22599999606609345,
        1.0
    ],
    "TimeSinceLastDealCompleted": 489,
    "TimeSinceLastDealOffered": 1049,
    "OfferedDeals": 47,
    "CompletedDeals": 43,
    "IsContractOffered": false,
    "OfferedContract": {
        "Payment": 0.0,
        "Products": {
            "entries": []
        },
        "DeliveryLocationGUID": "",
        "DeliveryWindow": {
            "IsEnabled": false,
            "WindowStartTime": 1200,
            "WindowEndTime": 1800
        },
        "Expires": false,
        "ExpiresAfter": 0,
        "PickupScheduleIndex": 0,
        "IsCounterOffer": false
    },
    "OfferedContractTime": {
        "elapsedDays": 52,
        "time": 2015
    },
    "TimeSincePlayerApproached": 1099354,
    "TimeSinceInstantDealOffered": 1099354,
    "HasBeenRecommended": false
}